[
    {
        "folder":  "1",
        "txtName":  "1.txt",
        "txtPath":  "C:\\Users\\used\\OneDrive\\Desktop\\بيع\\1\\1.txt",
        "content":  "اقل من سعر السوق لسرعه البيع🏄🏊🤽\r\n\r\nللبيع شاليه بينتهاس مميز  فى أمواچ_الساحل الشمالي 🏡🌊🌊 \r\n\r\n\r\nباطلاله مباشره علي حمام سباحه مباشرة 🌊 🌊 \r\n\r\nمساحه 146 م\r\n\r\n3نوم\r\n\r\n2حمام\r\n\r\nريسبشن\r\n\r\nمطبخ\r\n\r\nروف\r\n\r\n\r\nللبيع يشمل الفرش والاجهزة\r\n\r\nالسعر10.650.000\r\n\r\nللاستفسار يرجى الاتصال على\r\n01286394219",
        "ownImages":  [
                          "C:\\Users\\used\\OneDrive\\Desktop\\بيع\\1\\WhatsApp Image 2026-04-10 at 10.13.27 PM (1).jpeg",
                          "C:\\Users\\used\\OneDrive\\Desktop\\بيع\\1\\WhatsApp Image 2026-04-10 at 10.13.27 PM.jpeg",
                          "C:\\Users\\used\\OneDrive\\Desktop\\بيع\\1\\WhatsApp Image 2026-04-10 at 10.13.28 PM (1).jpeg",
                          "C:\\Users\\used\\OneDrive\\Desktop\\بيع\\1\\WhatsApp Image 2026-04-10 at 10.13.28 PM.jpeg",
                          "C:\\Users\\used\\OneDrive\\Desktop\\بيع\\1\\WhatsApp Image 2026-04-10 at 10.13.29 PM (1).jpeg",
                          "C:\\Users\\used\\OneDrive\\Desktop\\بيع\\1\\WhatsApp Image 2026-04-10 at 10.13.29 PM (2).jpeg",
                          "C:\\Users\\used\\OneDrive\\Desktop\\بيع\\1\\WhatsApp Image 2026-04-10 at 10.13.29 PM.jpeg"
                      ]
    },
    {
        "folder":  "2",
        "txtName":  "2.txt",
        "txtPath":  "C:\\Users\\used\\OneDrive\\Desktop\\بيع\\2\\2.txt",
        "content":  "🏖️ Senior Chalet for Sale at Hacienda Bay North coast\r\n🏖️ First Row1 ⛳ golF and lake\r\n🏖️ Prime location\r\n🏖️ Ground floor with Garden \r\n🏖️ Area : 220 m\r\n🏖️ Garden area : 320 m\r\n🏖️ Reception / Kitchen \r\n🏖️ Bedrooms 3 ( 2 masters)\r\n🏖️ Bathrooms 3\r\n🏖️ Driver room with bathroom / Nany room with bathroom\r\n🏖️ Fully Finished / Fully furnished \r\n🏖️ slot parking 2\r\n🏖️Price: 14.500.000 \r\n🏖️ For more details :01286490599",
        "ownImages":  [
                          "C:\\Users\\used\\OneDrive\\Desktop\\بيع\\2\\WhatsApp Image 2026-04-10 at 10.18.53 PM.jpeg",
                          "C:\\Users\\used\\OneDrive\\Desktop\\بيع\\2\\WhatsApp Image 2026-04-10 at 10.18.54 PM (1).jpeg",
                          "C:\\Users\\used\\OneDrive\\Desktop\\بيع\\2\\WhatsApp Image 2026-04-10 at 10.18.54 PM.jpeg",
                          "C:\\Users\\used\\OneDrive\\Desktop\\بيع\\2\\WhatsApp Image 2026-04-10 at 10.18.55 PM (1).jpeg",
                          "C:\\Users\\used\\OneDrive\\Desktop\\بيع\\2\\WhatsApp Image 2026-04-10 at 10.18.55 PM (2).jpeg",
                          "C:\\Users\\used\\OneDrive\\Desktop\\بيع\\2\\WhatsApp Image 2026-04-10 at 10.18.55 PM.jpeg"
                      ]
    },
    {
        "folder":  "3",
        "txtName":  "3.txt",
        "txtPath":  "C:\\Users\\used\\OneDrive\\Desktop\\بيع\\3\\3.txt",
        "content":  "villa stand alone sea front with private pool for sale @ hacienda Bay north cost \r\nLand area: 720\r\nBUA: 340 m\r\nGarden 500 m\r\nPrivate pool:120m\r\nConsists of \r\nReception \u0026 Dining \r\nKitchen \r\n4 master bedrooms \r\n6 bathroom \r\nSemi Finished \r\nReady to move \r\nUnder market price \r\nPrime location\r\nFirst Row sea\r\nPrice 50.950.000\r\nInstallment: 12.115.208\r\nQ: 904.000\r\nFor more info: 01228397313",
        "ownImages":  [
                          "C:\\Users\\used\\OneDrive\\Desktop\\بيع\\3\\WhatsApp Image 2026-04-10 at 10.22.50 PM.jpeg",
                          "C:\\Users\\used\\OneDrive\\Desktop\\بيع\\3\\WhatsApp Image 2026-04-10 at 10.22.51 PM (1).jpeg",
                          "C:\\Users\\used\\OneDrive\\Desktop\\بيع\\3\\WhatsApp Image 2026-04-10 at 10.22.51 PM (2).jpeg",
                          "C:\\Users\\used\\OneDrive\\Desktop\\بيع\\3\\WhatsApp Image 2026-04-10 at 10.22.51 PM (3).jpeg",
                          "C:\\Users\\used\\OneDrive\\Desktop\\بيع\\3\\WhatsApp Image 2026-04-10 at 10.22.51 PM.jpeg",
                          "C:\\Users\\used\\OneDrive\\Desktop\\بيع\\3\\WhatsApp Image 2026-04-10 at 10.22.52 PM.jpeg"
                      ]
    },
    {
        "folder":  "4",
        "txtName":  "4.txt",
        "txtPath":  "C:\\Users\\used\\OneDrive\\Desktop\\بيع\\4\\4.txt",
        "content":  "Marassi Marina \r\nChalet For Sale \r\nNear Pool \u0026 Marina \r\n\r\nArea 80 m\r\n1 Bedroom \r\n1 Bathroom \r\nKitchen \r\nReception \r\nFully A/C\r\nFully Furnished \r\n\r\nPrice 14,000,000\r\n01200092764",
        "ownImages":  [
                          "C:\\Users\\used\\OneDrive\\Desktop\\بيع\\4\\WhatsApp Image 2026-04-10 at 10.24.50 PM (1).jpeg",
                          "C:\\Users\\used\\OneDrive\\Desktop\\بيع\\4\\WhatsApp Image 2026-04-10 at 10.24.50 PM.jpeg",
                          "C:\\Users\\used\\OneDrive\\Desktop\\بيع\\4\\WhatsApp Image 2026-04-10 at 10.24.51 PM (1).jpeg",
                          "C:\\Users\\used\\OneDrive\\Desktop\\بيع\\4\\WhatsApp Image 2026-04-10 at 10.24.51 PM (2).jpeg",
                          "C:\\Users\\used\\OneDrive\\Desktop\\بيع\\4\\WhatsApp Image 2026-04-10 at 10.24.51 PM (3).jpeg",
                          "C:\\Users\\used\\OneDrive\\Desktop\\بيع\\4\\WhatsApp Image 2026-04-10 at 10.24.51 PM.jpeg"
                      ]
    },
    {
        "folder":  "5",
        "txtName":  "5.txt",
        "txtPath":  "C:\\Users\\used\\OneDrive\\Desktop\\بيع\\5\\5.txt",
        "content":  "🏖️ Senior Chalet for Sale at Hacienda Bay North coast\r\n🏖️ First Row1 ⛳ golF and lake\r\n🏖️ Prime location\r\n🏖️ Ground floor with Garden \r\n🏖️ Area : 220 m\r\n🏖️ Garden area : 320 m\r\n🏖️ Reception / Kitchen \r\n🏖️ Bedrooms 3 ( 2 masters)\r\n🏖️ Bathrooms 3\r\n🏖️ Driver room with bathroom / Nany room with bathroom\r\n🏖️ Fully Finished / Fully furnished \r\n🏖️A/C\r\n🏖️ slot parking 2\r\n🏖️Price: 14.500.000 \r\n🏖️ For more details :01286490599",
        "ownImages":  [
                          "C:\\Users\\used\\OneDrive\\Desktop\\بيع\\5\\WhatsApp Image 2026-04-10 at 10.27.16 PM.jpeg",
                          "C:\\Users\\used\\OneDrive\\Desktop\\بيع\\5\\WhatsApp Image 2026-04-10 at 10.30.14 PM (1).jpeg",
                          "C:\\Users\\used\\OneDrive\\Desktop\\بيع\\5\\WhatsApp Image 2026-04-10 at 10.30.14 PM.jpeg",
                          "C:\\Users\\used\\OneDrive\\Desktop\\بيع\\5\\WhatsApp Image 2026-04-10 at 10.30.15 PM.jpeg"
                      ]
    },
    {
        "folder":  "6",
        "txtName":  "6.txt",
        "txtPath":  "C:\\Users\\used\\OneDrive\\Desktop\\بيع\\6\\6.txt",
        "content":  "Marassi Marina Views \r\nChalet For Sale \r\nGround With Garden \r\nView Lagoon \r\n\r\nArea 131 m\r\nGarden 65 m\r\n2 Bedrooms - 1 Master\r\n2 Bathrooms \r\nKitchen \r\nReception \r\nFully A C \r\n\r\nD.p 23,500,000\r\nInstallments 3,500,000\r\nTotal 27,000,000\r\nاضافه صور مراسي \r\n01200092764",
        "ownImages":  [
                          "C:\\Users\\used\\OneDrive\\Desktop\\بيع\\6\\WhatsApp Image 2026-04-10 at 10.47.02 PM.jpeg",
                          "C:\\Users\\used\\OneDrive\\Desktop\\بيع\\6\\WhatsApp Image 2026-04-10 at 10.50.30 PM.jpeg",
                          "C:\\Users\\used\\OneDrive\\Desktop\\بيع\\6\\WhatsApp Image 2026-04-10 at 10.50.31 PM.jpeg",
                          "C:\\Users\\used\\OneDrive\\Desktop\\بيع\\6\\WhatsApp Image 2026-04-10 at 10.50.32 PM.jpeg",
                          "C:\\Users\\used\\OneDrive\\Desktop\\بيع\\6\\WhatsApp Image 2026-04-10 at 10.50.40 PM.jpeg"
                      ]
    },
    {
        "folder":  "7",
        "txtName":  "اقل من سعر السوق لسرعه البيع🏄🏊🤽.txt",
        "txtPath":  "C:\\Users\\used\\OneDrive\\Desktop\\بيع\\7\\اقل من سعر السوق لسرعه البيع🏄🏊🤽.txt",
        "content":  "اقل من سعر السوق لسرعه البيع🏄🏊🤽\r\n\r\nللبيع penthouse مميز  فى أمواچ_الساحل الشمالي 🏡🌊🌊\r\n\r\nمساحه 164 م\r\n\r\n٣نوم\r\n\r\n٢حمام\r\n\r\nريسبشن\r\n\r\nمطبخ\r\n\r\nروف 🌈\r\n\r\nللبيع يشمل الفرش والاجهزة\r\n\r\nالسعر10.600.000\r\n\r\nللاستفسار يرجى الاتصال على\r\n01286394219",
        "ownImages":  [
                          "C:\\Users\\used\\OneDrive\\Desktop\\بيع\\7\\2.jpeg",
                          "C:\\Users\\used\\OneDrive\\Desktop\\بيع\\7\\3.jpeg",
                          "C:\\Users\\used\\OneDrive\\Desktop\\بيع\\7\\WhatsApp Image 2026-04-09 at 10.47.46 AM.jpeg"
                      ]
    },
    {
        "folder":  "8",
        "txtName":  "Marassi Blanca.txt",
        "txtPath":  "C:\\Users\\used\\OneDrive\\Desktop\\بيع\\8\\Marassi Blanca.txt",
        "content":  "Marassi Blanca\r\nTwin House For Sale \r\nDirect Golf\r\nPrivate Pool\r\n\r\nArea 440 m\r\n4 Bedroom \r\n4 Bathrooms \r\nKitchen \r\nReception \r\nMaid Room \r\nGarage \r\n\r\nPrice 53,000,000\r\n01200092764\r\n",
        "ownImages":  [
                          "C:\\Users\\used\\OneDrive\\Desktop\\بيع\\8\\WhatsApp Image 2026-04-09 at 10.45.04 AM.jpeg",
                          "C:\\Users\\used\\OneDrive\\Desktop\\بيع\\8\\WhatsApp Image 2026-04-09 at 10.45.05 AM (1).jpeg",
                          "C:\\Users\\used\\OneDrive\\Desktop\\بيع\\8\\WhatsApp Image 2026-04-09 at 10.45.05 AM.jpeg",
                          "C:\\Users\\used\\OneDrive\\Desktop\\بيع\\8\\WhatsApp Image 2026-04-09 at 10.45.06 AM.jpeg",
                          "C:\\Users\\used\\OneDrive\\Desktop\\بيع\\8\\WhatsApp Image 2026-04-09 at 10.45.07 AM (1).jpeg",
                          "C:\\Users\\used\\OneDrive\\Desktop\\بيع\\8\\WhatsApp Image 2026-04-09 at 10.45.07 AM.jpeg",
                          "C:\\Users\\used\\OneDrive\\Desktop\\بيع\\8\\WhatsApp Image 2026-04-09 at 10.45.08 AM (1).jpeg",
                          "C:\\Users\\used\\OneDrive\\Desktop\\بيع\\8\\WhatsApp Image 2026-04-09 at 10.45.08 AM.jpeg",
                          "C:\\Users\\used\\OneDrive\\Desktop\\بيع\\8\\WhatsApp Image 2026-04-09 at 10.45.09 AM.jpeg",
                          "C:\\Users\\used\\OneDrive\\Desktop\\بيع\\8\\WhatsApp Image 2026-04-09 at 10.45.10 AM (1).jpeg",
                          "C:\\Users\\used\\OneDrive\\Desktop\\بيع\\8\\WhatsApp Image 2026-04-09 at 10.45.10 AM.jpeg",
                          "C:\\Users\\used\\OneDrive\\Desktop\\بيع\\8\\WhatsApp Image 2026-04-09 at 10.45.11 AM (1).jpeg",
                          "C:\\Users\\used\\OneDrive\\Desktop\\بيع\\8\\WhatsApp Image 2026-04-09 at 10.45.11 AM.jpeg",
                          "C:\\Users\\used\\OneDrive\\Desktop\\بيع\\8\\WhatsApp Image 2026-04-09 at 10.45.12 AM (1).jpeg",
                          "C:\\Users\\used\\OneDrive\\Desktop\\بيع\\8\\WhatsApp Image 2026-04-09 at 10.45.12 AM.jpeg",
                          "C:\\Users\\used\\OneDrive\\Desktop\\بيع\\8\\WhatsApp Image 2026-04-09 at 10.45.13 AM (1).jpeg",
                          "C:\\Users\\used\\OneDrive\\Desktop\\بيع\\8\\WhatsApp Image 2026-04-09 at 10.45.13 AM.jpeg",
                          "C:\\Users\\used\\OneDrive\\Desktop\\بيع\\8\\WhatsApp Image 2026-04-09 at 10.45.14 AM (1).jpeg",
                          "C:\\Users\\used\\OneDrive\\Desktop\\بيع\\8\\WhatsApp Image 2026-04-09 at 10.45.14 AM.jpeg",
                          "C:\\Users\\used\\OneDrive\\Desktop\\بيع\\8\\WhatsApp Image 2026-04-09 at 10.45.15 AM (1).jpeg",
                          "C:\\Users\\used\\OneDrive\\Desktop\\بيع\\8\\WhatsApp Image 2026-04-09 at 10.45.15 AM.jpeg",
                          "C:\\Users\\used\\OneDrive\\Desktop\\بيع\\8\\WhatsApp Image 2026-04-09 at 10.45.16 AM (1).jpeg",
                          "C:\\Users\\used\\OneDrive\\Desktop\\بيع\\8\\WhatsApp Image 2026-04-09 at 10.45.16 AM (2).jpeg",
                          "C:\\Users\\used\\OneDrive\\Desktop\\بيع\\8\\WhatsApp Image 2026-04-09 at 10.45.16 AM (3).jpeg",
                          "C:\\Users\\used\\OneDrive\\Desktop\\بيع\\8\\WhatsApp Image 2026-04-09 at 10.45.16 AM (4).jpeg",
                          "C:\\Users\\used\\OneDrive\\Desktop\\بيع\\8\\WhatsApp Image 2026-04-09 at 10.45.16 AM.jpeg",
                          "C:\\Users\\used\\OneDrive\\Desktop\\بيع\\8\\WhatsApp Image 2026-04-09 at 10.45.17 AM (1).jpeg",
                          "C:\\Users\\used\\OneDrive\\Desktop\\بيع\\8\\WhatsApp Image 2026-04-09 at 10.45.17 AM.jpeg",
                          "C:\\Users\\used\\OneDrive\\Desktop\\بيع\\8\\WhatsApp Image 2026-04-09 at 10.45.18 AM.jpeg",
                          "C:\\Users\\used\\OneDrive\\Desktop\\بيع\\8\\WhatsApp Image 2026-04-09 at 10.45.19 AM.jpeg"
                      ]
    },
    {
        "folder":  "9",
        "txtName":  "Marassi Marina.txt",
        "txtPath":  "C:\\Users\\used\\OneDrive\\Desktop\\بيع\\9\\Marassi Marina.txt",
        "content":  "Marassi Marina\r\nChalet For Sale \r\nFacing North \r\nSecond Row Marina \r\nNear Pool\r\n\r\nArea 130 m\r\n2 Bedrooms \r\n2 Bathrooms \r\nKitchen \r\nReception \r\nFully A-C \r\nFully Furnished \r\n\r\nPrice 23,000,000\r\nCode AZ25\r\n01200092764\r\nاضافه صور مراسي",
        "ownImages":  [

                      ]
    },
    {
        "folder":  "10",
        "txtName":  "Golf villa for sale @ hacienda Bay.txt",
        "txtPath":  "C:\\Users\\used\\OneDrive\\Desktop\\بيع\\10\\Golf villa for sale @ hacienda Bay.txt",
        "content":  "Golf villa for sale @ hacienda Bay north cost \r\n\r\nLand area: 690\r\nBUA: 348m\r\nGarden 342m\r\nConsists of \r\nReception \r\nKitchen \r\n4 master bedrooms \r\n6 bathroom \r\nDriver room with bathroom \r\nNany room with bathroom \r\nFully Finished\r\nFully Furnished \r\nBahary\r\nReady to move \r\nPrice 30.000.000 قابل للتفاوض\r\nFor more info: 01228397313",
        "ownImages":  [

                      ]
    },
    {
        "folder":  "11",
        "txtName":  "اقل من سعر السوق لسرعه البيع🏄🏊🤽.txt",
        "txtPath":  "C:\\Users\\used\\OneDrive\\Desktop\\بيع\\11\\اقل من سعر السوق لسرعه البيع🏄🏊🤽.txt",
        "content":  "اقل من سعر السوق لسرعه البيع🏄🏊🤽\r\n\r\nللبيع شاليه دور ارضي   مميز  فى أمواچ_الساحل الشمالي 🏡🌊🌊\r\n\r\n\r\nمساحه 146م\r\n\r\n٣نوم\r\n\r\n٢حمام\r\n\r\nريسبشن\r\n\r\nمطبخ\r\n\r\nحديقه علي البول 🌈\r\n\r\nللبيع يشمل الفرش والاجهزة\r\n\r\n\r\nالسعر10.750.000\r\n\r\nللاستفسار يرجى الاتصال على\r\n01286394219",
        "ownImages":  [

                      ]
    },
    {
        "folder":  "12",
        "txtName":  "اقل من سعر السوق لسرعه البيع🏄🏊🤽.txt",
        "txtPath":  "C:\\Users\\used\\OneDrive\\Desktop\\بيع\\12\\اقل من سعر السوق لسرعه البيع🏄🏊🤽.txt",
        "content":  "اقل من سعر السوق لسرعه البيع🏄🏊🤽\r\n\r\nللبيع penthouse مميز  فى أمواچ_الساحل الشمالي 🏡🌊🌊\r\n\r\n\r\nمساحه 127 م\r\n\r\n٢نوم\r\n\r\n٢حمام\r\n\r\nريسبشن\r\n\r\nمطبخ\r\n\r\nروف 🌈\r\n\r\nللبيع يشمل الفرش والاجهزة\r\n\r\nالسعر9.000.000\r\n\r\nللاستفسار يرجى الاتصال على\r\n01286394219",
        "ownImages":  [

                      ]
    },
    {
        "folder":  "13",
        "txtName":  "Hacienda West - Palm Hills.txt",
        "txtPath":  "C:\\Users\\used\\OneDrive\\Desktop\\بيع\\13\\Hacienda West - Palm Hills.txt",
        "content":  "Hacienda West - Palm Hills \r\nPhase : Almond\r\nSecond Floor \r\nArea 114 m\r\n2 Bedrooms - 1 Master\r\n2 Bathrooms \r\nKitchen \r\nReception \r\nFully Finished \r\nDelivery 6-2027\r\n\r\nD.p 6,950,000 \r\nInstallments 3,778,410 \r\nTotal 10,728,410 \r\n\r\nNext Installment 3-2026\r\n\r\nNext Maintenance 12-2026 : 102,000\r\n\r\n01200092764",
        "ownImages":  [

                      ]
    },
    {
        "folder":  "14",
        "txtName":  "Hacienda West - Palm Hills.txt",
        "txtPath":  "C:\\Users\\used\\OneDrive\\Desktop\\بيع\\14\\Hacienda West - Palm Hills.txt",
        "content":  "Hacienda West - Palm Hills \r\nPhase : Mastic\r\nArea 99 m\r\n2 Bedrooms - 1 Master\r\n2 Bathrooms \r\nKitchen \r\nReception \r\nFully Finished \r\nDelivery 2027\r\nD.p 5,720,000\r\nInstallments 4,070,000\r\nTotal 9,790,000\r\n\r\nNext Installment 5-2026\r\n\r\nNext Maintenance \r\n2-2027 \r\n110,293\r\n\r\n01200092764\r\nاضافه صور هاسيندا ويست",
        "ownImages":  [

                      ]
    },
    {
        "folder":  "15",
        "txtName":  "penthouse corner for sale at hacien.txt",
        "txtPath":  "C:\\Users\\used\\OneDrive\\Desktop\\بيع\\15\\penthouse corner for sale at hacien.txt",
        "content":  "penthouse corner for sale at hacienda west\r\n(almond)\r\nSea view\r\n4rd typical floor\r\nConsists of \r\nReception \r\nKitchen \r\n2 bedrooms \r\n3 bathrooms \r\nArea: Bua 111.5 + 21 penthouse + 53 Roof\r\nTotal area: 185.5 \r\nDown payment: 8,000,000\r\nRemaining: 6,489,910\r\nDelivery date 12/2026",
        "ownImages":  [

                      ]
    },
    {
        "folder":  "16",
        "txtName":  "Chalet penthouse sea view for sale.txt",
        "txtPath":  "C:\\Users\\used\\OneDrive\\Desktop\\بيع\\16\\Chalet penthouse sea view for sale.txt",
        "content":  "Chalet penthouse sea view for sale at hacienda west \r\nAlmond phase \r\n ( 4rd typical floor ) \r\n\r\n Bua: 111.5\r\n Roof: 75\r\nConsists of \r\nReception \r\nKitchen \r\n2 bedrooms \r\n3 bathrooms \r\n\r\nDown payment: 7,800,000\r\nRemaining:6,729,000\r\nTotal: 14.529.000\r\nDelivery date 2026",
        "ownImages":  [

                      ]
    },
    {
        "folder":  "17",
        "txtName":  "Hacienda West - Palm Hills 💥.txt",
        "txtPath":  "C:\\Users\\used\\OneDrive\\Desktop\\بيع\\17\\Hacienda West - Palm Hills 💥.txt",
        "content":  "Hacienda West - Palm Hills 💥 \r\nUnder Market Price \r\nPhase : Mastic\r\nArea 99 m\r\n2 Bedrooms - 1 Master\r\n2 Bathrooms \r\nKitchen \r\nReception \r\nFully Finished \r\nDelivery 2027\r\nD.p 5,300,000\r\nInstallments 4,070,000\r\nTotal 9,370,000\r\n\r\nNext Installment 5-2026\r\n\r\nNext Maintenance \r\n2-2027 \r\n110,293\r\n\r\n01200092764\r\n",
        "ownImages":  [

                      ]
    },
    {
        "folder":  "18",
        "txtName":  "Update.txt",
        "txtPath":  "C:\\Users\\used\\OneDrive\\Desktop\\بيع\\18\\Update.txt",
        "content":  "Update \r\nHacienda West - Palm Hills 💥 \r\n\r\nPhase : Almond\r\nSecond Floor \r\nArea 114 m\r\n2 Bedrooms - 1 Master\r\n2 Bathrooms \r\nKitchen \r\nReception \r\nFully Finished \r\nDelivery 6-2027\r\n\r\nD.p 6,500,000 \r\nInstallments 3,778,410 \r\nTotal 10,278,410 \r\n\r\nNext Installment 3-2026\r\n\r\nNext Maintenance 12-2026 : 102,000\r\n\r\n01200092764",
        "ownImages":  [

                      ]
    },
    {
        "folder":  "19",
        "txtName":  "Hacienda West - Mastic.txt",
        "txtPath":  "C:\\Users\\used\\OneDrive\\Desktop\\بيع\\19\\Hacienda West - Mastic.txt",
        "content":  "Hacienda West - Mastic \r\nGround floor \r\nPrime Location \r\n\r\nArea 100 m\r\nGarden 35 m\r\n2 Bedrooms Master\r\n3 Bathrooms \r\nKitchen \r\nReception \r\nFully Finished \r\nDelivery 2027\r\nNext Installment 8-2027\r\n\r\nD.p 6,200,000\r\nInstallments 4,100,000\r\nTotal 10,300,000",
        "ownImages":  [

                      ]
    },
    {
        "folder":  "20",
        "txtName":  "Under market price.txt",
        "txtPath":  "C:\\Users\\used\\OneDrive\\Desktop\\بيع\\20\\Under market price.txt",
        "content":  "Under market price \r\nPrime location \r\nSenior chalet for sale @hacienda bay north cost \r\n2nd row golf \r\nFirst floor with roof\r\nBUA: 220\r\nRoof :90\r\nConsists of \r\nReception \r\nKitchen \r\nBedrooms: 4\r\nMaster bedrooms 2\r\nBathroom: 3\r\nNo furnished \r\nFully Finished \r\nA/C\r\nPrice : 12.500.000\r\nFor more info: 01228397313",
        "ownImages":  [

                      ]
    },
    {
        "folder":  "21",
        "txtName":  "Under market price.txt",
        "txtPath":  "C:\\Users\\used\\OneDrive\\Desktop\\بيع\\21\\Under market price.txt",
        "content":  "Under market price \r\nPrime location \r\nSenior chalet for sale @hacienda bay north cost \r\n2nd row golf \r\nFirst floor with roof\r\nBUA: 220\r\nRoof :90\r\nConsists of \r\nReception \r\nKitchen \r\nBedrooms: 4\r\nMaster bedrooms 2\r\nBathroom: 3\r\nNo furnished \r\nFully Finished \r\nA/C\r\nPrice : 12.000.000\r\nFor more info: 01228397313",
        "ownImages":  [

                      ]
    },
    {
        "folder":  "22",
        "txtName":  "Junior chalet for sale @hacienda ba.txt",
        "txtPath":  "C:\\Users\\used\\OneDrive\\Desktop\\بيع\\22\\Junior chalet for sale @hacienda ba.txt",
        "content":  "Junior chalet for sale @hacienda bay north cost\r\nSecond row golf ⛳ \r\nGround with Garden\r\nBUA: 175\r\nGarden :120m\r\nConsists of:\u003e\r\nReception \r\nKitchen \r\nBedrooms: 3\r\nMaster bedrooms 2\r\nBathroom: 3\r\nFully furnished \r\nFully Finished \r\nPrice : 10.750.000",
        "ownImages":  [

                      ]
    },
    {
        "folder":  "23",
        "txtName":  "اقل من سعر السوق لسرعه البيع🏄🏊🤽.txt",
        "txtPath":  "C:\\Users\\used\\OneDrive\\Desktop\\بيع\\23\\اقل من سعر السوق لسرعه البيع🏄🏊🤽.txt",
        "content":  "اقل من سعر السوق لسرعه البيع🏄🏊🤽\r\n\r\nللبيع شاليه دور اول  مميز  فى أمواچ_الساحل الشمالي 🏡🌊🌊\r\n\r\n\r\nمساحه 146 م\r\n\r\n3نوم\r\n\r\n2حمام\r\n\r\nريسبشن\r\n\r\nمطبخ\r\n\r\nللبيع يشمل الفرش والاجهزة\r\n\r\nالسعر9.000.000\r\n\r\nللاستفسار يرجى الاتصال على\r\n01286394219",
        "ownImages":  [

                      ]
    },
    {
        "folder":  "24",
        "txtName":  "اقل من سعر السوق لسرعه البيع🏄🏊🤽.txt",
        "txtPath":  "C:\\Users\\used\\OneDrive\\Desktop\\بيع\\24\\اقل من سعر السوق لسرعه البيع🏄🏊🤽.txt",
        "content":  "اقل من سعر السوق لسرعه البيع🏄🏊🤽\r\n\r\nللبيع شاليه بينتهاوس  مميز  فى أمواچ_الساحل الشمالي 🏡🌊🌊\r\n\r\n\r\nمساحه 115 م\r\n\r\n2نوم\r\n\r\n2حمام\r\n\r\nريسبشن\r\n\r\nمطبخ\r\n\r\nروف\r\n\r\nللبيع يشمل الفرش والاجهزة\r\n\r\nالسعر8.400.000\r\n\r\nللاستفسار يرجى الاتصال على\r\n01286394219س",
        "ownImages":  [

                      ]
    },
    {
        "folder":  "25",
        "txtName":  "CHALET \u0026 for sale @ hacienda west.txt",
        "txtPath":  "C:\\Users\\used\\OneDrive\\Desktop\\بيع\\25\\CHALET \u0026 for sale @ hacienda west.txt",
        "content":  "CHALET \u0026 for sale @ hacienda west \r\nHazel phase \r\n2nd floor \r\nB.U.A: 92m\r\nTerrace: 15m\r\nConsists of \r\n2 bedrooms \r\n2 bathrooms\r\nReception \u0026 Dining \r\nKitchen \r\nFully Finished \r\nReady to move \r\n\r\nTotal price Chalet: 9.630.000\r\nDownpayment: 8.230.000\r\nRemaining: 1,400.000\r\nQ: 73.750\r\n+ Maintenance’s fully paid\r\nFor more details: 01228397313",
        "ownImages":  [

                      ]
    },
    {
        "folder":  "26",
        "txtName":  "اقل من سعر السوق لسرعه البيع🏄🏊🤽.txt",
        "txtPath":  "C:\\Users\\used\\OneDrive\\Desktop\\بيع\\26\\اقل من سعر السوق لسرعه البيع🏄🏊🤽.txt",
        "content":  "اقل من سعر السوق لسرعه البيع🏄🏊🤽\r\n\r\nللبيع شاليه دور اول  مميز  فى أمواچ_الساحل الشمالي 🏡🌊🌊 \r\n \r\n\r\nمساحه 120 م\r\n\r\n2نوم\r\n\r\n2حمام\r\n\r\nريسبشن\r\n\r\nمطبخ\r\n\r\n\r\nللبيع يشمل الفرش والاجهزة\r\n\r\nالسعر9.000.000\r\n\r\nللاستفسار يرجى الاتصال على\r\n01286394219",
        "ownImages":  [

                      ]
    },
    {
        "folder":  "27",
        "txtName":  "اقل من سعر السوق لسرعه البيع🏄🏊🤽.txt",
        "txtPath":  "C:\\Users\\used\\OneDrive\\Desktop\\بيع\\27\\اقل من سعر السوق لسرعه البيع🏄🏊🤽.txt",
        "content":  "اقل من سعر السوق لسرعه البيع🏄🏊🤽\r\n\r\nللبيع شاليه دور اول  مميز  فى أمواچ_الساحل الشمالي 🏡🌊🌊 \r\n \r\n\r\nمساحه 146 م\r\n\r\n3نوم\r\n\r\n2حمام\r\n\r\nريسبشن\r\n\r\nمطبخ\r\n\r\n\r\nللبيع يشمل الفرش والاجهزة\r\n\r\nالسعر11.000.000\r\n\r\nللاستفسار يرجى الاتصال على\r\n01286394219",
        "ownImages":  [

                      ]
    },
    {
        "folder":  "28",
        "txtName":  "اقل من سعر السوق لسرعه البيع🏄🏊🤽.txt",
        "txtPath":  "C:\\Users\\used\\OneDrive\\Desktop\\بيع\\28\\اقل من سعر السوق لسرعه البيع🏄🏊🤽.txt",
        "content":  "اقل من سعر السوق لسرعه البيع🏄🏊🤽\r\n\r\nللبيع شاليه دور اول  مميز  فى أمواچ_الساحل الشمالي 🏡🌊🌊 \r\n \r\n\r\nمساحه 120 م\r\n\r\n2نوم\r\n\r\n2حمام\r\n\r\nريسبشن\r\n\r\nمطبخ\r\n\r\n\r\nللبيع يشمل الفرش والاجهزة\r\n\r\nالسعر9.000.000\r\n\r\nللاستفسار يرجى الاتصال على\r\n01286394219",
        "ownImages":  [

                      ]
    },
    {
        "folder":  "29",
        "txtName":  "Prime location.txt",
        "txtPath":  "C:\\Users\\used\\OneDrive\\Desktop\\بيع\\29\\Prime location.txt",
        "content":  "Prime location \r\nHazel Chalet - for sale @ hacienda west \r\nGround with garden \r\nBUA: 150m\r\nGarden: 65m\r\nConsists of \r\nReception \u0026 Dining \r\nKitchen \r\n3 bedroom Master \r\n4 bathrooms\r\nFully finished \r\nReady to move \r\nMaintenance paid\r\nDown payment: 11.000.000\r\nInstallment: 1.509.000\r\nFor more details: 01228397313",
        "ownImages":  [

                      ]
    },
    {
        "folder":  "30",
        "txtName":  "Marassi Marina Views.txt",
        "txtPath":  "C:\\Users\\used\\OneDrive\\Desktop\\بيع\\30\\Marassi Marina Views.txt",
        "content":  "Marassi Marina Views \r\nChalet For Sale \r\nGround With Garden \r\nView Lagoon \r\n\r\nArea 131 m\r\nGarden 65 m\r\n2 Bedrooms - 1 Master\r\n2 Bathrooms \r\nKitchen \r\nReception \r\nFully A C \r\n\r\nD.p 23,500,000\r\nInstallments 3,500,000\r\nTotal 27,000,000\r\nاضافه صور مراسي \r\n01200092764",
        "ownImages":  [

                      ]
    },
    {
        "folder":  "31",
        "txtName":  "Ground Chalet for sale at Amwaj - N.txt",
        "txtPath":  "C:\\Users\\used\\OneDrive\\Desktop\\بيع\\31\\Ground Chalet for sale at Amwaj - N.txt",
        "content":  "Ground Chalet for sale at Amwaj - North Coast \r\n\r\nArea : 115m\r\n2 Bedrooms\r\n2 Bathrooms\r\nReception\r\n\r\nGarden \r\nFully finished \r\nFully furnished \r\n\r\nPrice : 8.000.000",
        "ownImages":  [
                          "C:\\Users\\used\\OneDrive\\Desktop\\بيع\\31\\WhatsApp Image 2026-04-09 at 10.44.43 AM.jpeg",
                          "C:\\Users\\used\\OneDrive\\Desktop\\بيع\\31\\WhatsApp Image 2026-04-09 at 10.44.44 AM (1).jpeg",
                          "C:\\Users\\used\\OneDrive\\Desktop\\بيع\\31\\WhatsApp Image 2026-04-09 at 10.44.44 AM (2).jpeg",
                          "C:\\Users\\used\\OneDrive\\Desktop\\بيع\\31\\WhatsApp Image 2026-04-09 at 10.44.44 AM.jpeg",
                          "C:\\Users\\used\\OneDrive\\Desktop\\بيع\\31\\WhatsApp Image 2026-04-09 at 10.44.45 AM (1).jpeg",
                          "C:\\Users\\used\\OneDrive\\Desktop\\بيع\\31\\WhatsApp Image 2026-04-09 at 10.44.45 AM.jpeg",
                          "C:\\Users\\used\\OneDrive\\Desktop\\بيع\\31\\WhatsApp Image 2026-04-09 at 10.44.46 AM (1).jpeg",
                          "C:\\Users\\used\\OneDrive\\Desktop\\بيع\\31\\WhatsApp Image 2026-04-09 at 10.44.46 AM.jpeg"
                      ]
    },
    {
        "folder":  "32",
        "txtName":  "Under market price.txt",
        "txtPath":  "C:\\Users\\used\\OneDrive\\Desktop\\بيع\\32\\Under market price.txt",
        "content":  "Under market price \r\nPrime location \r\nSenior chalet for sale @hacienda bay north cost \r\n2nd row golf \r\nFirst floor with roof\r\nBUA: 220\r\nRoof :90\r\nConsists of \r\nReception \r\nKitchen \r\nBedrooms: 4\r\nMaster bedrooms 2\r\nBathroom: 3\r\nNo furnished \r\nFully Finished \r\nA/C\r\nPrice : 12.500.000\r\nFor more info: 01228397313",
        "ownImages":  [
                          "C:\\Users\\used\\OneDrive\\Desktop\\بيع\\32\\WhatsApp Image 2026-04-09 at 10.44.32 AM (1).jpeg",
                          "C:\\Users\\used\\OneDrive\\Desktop\\بيع\\32\\WhatsApp Image 2026-04-09 at 10.44.32 AM.jpeg",
                          "C:\\Users\\used\\OneDrive\\Desktop\\بيع\\32\\WhatsApp Image 2026-04-09 at 10.44.33 AM (1).jpeg",
                          "C:\\Users\\used\\OneDrive\\Desktop\\بيع\\32\\WhatsApp Image 2026-04-09 at 10.44.33 AM (2).jpeg",
                          "C:\\Users\\used\\OneDrive\\Desktop\\بيع\\32\\WhatsApp Image 2026-04-09 at 10.44.33 AM.jpeg",
                          "C:\\Users\\used\\OneDrive\\Desktop\\بيع\\32\\WhatsApp Image 2026-04-09 at 10.44.34 AM (1).jpeg",
                          "C:\\Users\\used\\OneDrive\\Desktop\\بيع\\32\\WhatsApp Image 2026-04-09 at 10.44.34 AM.jpeg",
                          "C:\\Users\\used\\OneDrive\\Desktop\\بيع\\32\\WhatsApp Image 2026-04-09 at 10.44.35 AM (1).jpeg",
                          "C:\\Users\\used\\OneDrive\\Desktop\\بيع\\32\\WhatsApp Image 2026-04-09 at 10.44.35 AM (2).jpeg",
                          "C:\\Users\\used\\OneDrive\\Desktop\\بيع\\32\\WhatsApp Image 2026-04-09 at 10.44.35 AM.jpeg"
                      ]
    },
    {
        "folder":  "33",
        "txtName":  "Marassi Marina Views.txt",
        "txtPath":  "C:\\Users\\used\\OneDrive\\Desktop\\بيع\\33\\Marassi Marina Views.txt",
        "content":  "Marassi Marina Views\r\nChalet For Sale \r\nGround With Garden \r\nNear Marina \u0026 Lagoon \r\n\r\nArea 127 m\r\nGarden 70 m\r\n2 Bedrooms - 1 Master\r\n2 Bathrooms \r\nKitchen \r\nReception \r\nFully A-C \r\nFully Furnished \r\n\r\nPrice 26,000,000\r\n\r\n01200092764",
        "ownImages":  [
                          "C:\\Users\\used\\OneDrive\\Desktop\\بيع\\33\\WhatsApp Image 2026-04-09 at 10.43.10 AM (1).jpeg",
                          "C:\\Users\\used\\OneDrive\\Desktop\\بيع\\33\\WhatsApp Image 2026-04-09 at 10.43.10 AM (2).jpeg",
                          "C:\\Users\\used\\OneDrive\\Desktop\\بيع\\33\\WhatsApp Image 2026-04-09 at 10.43.10 AM (3).jpeg",
                          "C:\\Users\\used\\OneDrive\\Desktop\\بيع\\33\\WhatsApp Image 2026-04-09 at 10.43.10 AM.jpeg",
                          "C:\\Users\\used\\OneDrive\\Desktop\\بيع\\33\\WhatsApp Image 2026-04-09 at 10.43.11 AM.jpeg"
                      ]
    },
    {
        "folder":  "34",
        "txtName":  "Untitled.txt",
        "txtPath":  "C:\\Users\\used\\OneDrive\\Desktop\\بيع\\34\\Untitled.txt",
        "content":  "💥 Standalone Villa For sale - Marassi - Blanca - North Coast  💥\r\n🏖️ Facing North / Prime location\r\n🏖️ Total land area : 540 M\r\n🏖️ Built area : 395 M\r\n🏖️ Consists of\r\n🏖️ Roof\r\n🏖️ reception\r\n🏖️ kitchen \r\n🏖️ 5 bedrooms \r\n🏖️ 5 bathrooms \r\n🏖️ Maid room with bathrooms\r\n🏖️ Fully finished\r\n🏖️ Fully furnished\r\n🏖️ Fully AC\r\n🏖️ Garage\r\n🏖️ price : 54.000.000\r\n🏖️ For more details : 01283399732\r\nWe also have variety of units in marassi, hacienda white, hacienda bay, seashell, amwaj, telal, contact us for more information",
        "ownImages":  [
                          "C:\\Users\\used\\OneDrive\\Desktop\\بيع\\34\\WhatsApp Image 2026-04-09 at 10.42.37 AM (1).jpeg",
                          "C:\\Users\\used\\OneDrive\\Desktop\\بيع\\34\\WhatsApp Image 2026-04-09 at 10.42.37 AM.jpeg",
                          "C:\\Users\\used\\OneDrive\\Desktop\\بيع\\34\\WhatsApp Image 2026-04-09 at 10.42.38 AM (1).jpeg",
                          "C:\\Users\\used\\OneDrive\\Desktop\\بيع\\34\\WhatsApp Image 2026-04-09 at 10.42.38 AM.jpeg",
                          "C:\\Users\\used\\OneDrive\\Desktop\\بيع\\34\\WhatsApp Image 2026-04-09 at 10.42.39 AM (1).jpeg",
                          "C:\\Users\\used\\OneDrive\\Desktop\\بيع\\34\\WhatsApp Image 2026-04-09 at 10.42.39 AM.jpeg",
                          "C:\\Users\\used\\OneDrive\\Desktop\\بيع\\34\\WhatsApp Image 2026-04-09 at 10.42.40 AM.jpeg"
                      ]
    },
    {
        "folder":  "35",
        "txtName":  "Senior chalet for sale @hacienda ba.txt",
        "txtPath":  "C:\\Users\\used\\OneDrive\\Desktop\\بيع\\35\\Senior chalet for sale @hacienda ba.txt",
        "content":  "Senior chalet for sale @hacienda bay north cost \r\nFirst row golf \r\n First floor with roof  \r\nBUA: 220\r\nRoof :90\r\nBedrooms: 4\r\nMaster bedrooms 2\r\nBathroom: 3\r\nFully furnished \r\nFully Finished \r\nA/C\r\nPrice 15.500. 000\r\nFor more info: 012287397313",
        "ownImages":  [
                          "C:\\Users\\used\\OneDrive\\Desktop\\بيع\\35\\WhatsApp Image 2026-04-09 at 10.41.43 AM.jpeg",
                          "C:\\Users\\used\\OneDrive\\Desktop\\بيع\\35\\WhatsApp Image 2026-04-09 at 10.41.44 AM (1).jpeg",
                          "C:\\Users\\used\\OneDrive\\Desktop\\بيع\\35\\WhatsApp Image 2026-04-09 at 10.41.44 AM.jpeg",
                          "C:\\Users\\used\\OneDrive\\Desktop\\بيع\\35\\WhatsApp Image 2026-04-09 at 10.41.45 AM (1).jpeg",
                          "C:\\Users\\used\\OneDrive\\Desktop\\بيع\\35\\WhatsApp Image 2026-04-09 at 10.41.45 AM.jpeg",
                          "C:\\Users\\used\\OneDrive\\Desktop\\بيع\\35\\WhatsApp Image 2026-04-09 at 10.41.46 AM.jpeg",
                          "C:\\Users\\used\\OneDrive\\Desktop\\بيع\\35\\WhatsApp Image 2026-04-09 at 10.41.47 AM (1).jpeg",
                          "C:\\Users\\used\\OneDrive\\Desktop\\بيع\\35\\WhatsApp Image 2026-04-09 at 10.41.47 AM.jpeg",
                          "C:\\Users\\used\\OneDrive\\Desktop\\بيع\\35\\WhatsApp Image 2026-04-09 at 10.41.48 AM.jpeg",
                          "C:\\Users\\used\\OneDrive\\Desktop\\بيع\\35\\WhatsApp Image 2026-04-09 at 10.41.49 AM (1).jpeg",
                          "C:\\Users\\used\\OneDrive\\Desktop\\بيع\\35\\WhatsApp Image 2026-04-09 at 10.41.49 AM.jpeg",
                          "C:\\Users\\used\\OneDrive\\Desktop\\بيع\\35\\WhatsApp Image 2026-04-09 at 10.41.50 AM (1).jpeg",
                          "C:\\Users\\used\\OneDrive\\Desktop\\بيع\\35\\WhatsApp Image 2026-04-09 at 10.41.50 AM.jpeg",
                          "C:\\Users\\used\\OneDrive\\Desktop\\بيع\\35\\WhatsApp Image 2026-04-09 at 10.41.51 AM.jpeg"
                      ]
    },
    {
        "folder":  "36",
        "txtName":  "🔥لقطه ..لسرعه البيع سينيور شاليه ا.txt",
        "txtPath":  "C:\\Users\\used\\OneDrive\\Desktop\\بيع\\36\\🔥لقطه ..لسرعه البيع سينيور شاليه ا.txt",
        "content":  "🔥لقطه ..لسرعه البيع سينيور شاليه اول صف جولف متشطب ومفروش فقط  14.500.000🔥\r\n🏖️ Senior Chalet for Sale at Hacienda Bay North coast\r\n🏖️ First Row1 golf ⛳ and lake\r\n🏖️ Prime location\r\n🏖️ Ground floor with Garden \r\n🏖️ Area : 220m\r\n🏖️ Garden area : 250m\r\n🏖️ Reception\r\n🏖️ Kitchen\r\n🏖️ Bedrooms 3 ( 2 masters)\r\n🏖️ Bathrooms 3\r\n🏖️ Driver room with bathroom\r\n🏖️ Fully finished\r\n🏖️ Fully furnished\r\n🏖️ slot parking 2\r\n🏖️ A/C\r\n🏖️ For more details : 01283399732\r\nWe also have variety of units in marassi, hacienda white, hacienda bay, seashell, amwaj, telal, contact us for more information",
        "ownImages":  [
                          "C:\\Users\\used\\OneDrive\\Desktop\\بيع\\36\\WhatsApp Image 2026-04-09 at 10.39.30 AM.jpeg",
                          "C:\\Users\\used\\OneDrive\\Desktop\\بيع\\36\\WhatsApp Image 2026-04-09 at 10.39.31 AM.jpeg",
                          "C:\\Users\\used\\OneDrive\\Desktop\\بيع\\36\\WhatsApp Image 2026-04-09 at 10.39.32 AM.jpeg"
                      ]
    },
    {
        "folder":  "37",
        "txtName":  "Senior Chalet for Sale @ Hacienda B.txt",
        "txtPath":  "C:\\Users\\used\\OneDrive\\Desktop\\بيع\\37\\Senior Chalet for Sale @ Hacienda B.txt",
        "content":  "Senior Chalet for Sale @ Hacienda Bay North coast\r\nFirst Row1 ⛳ golF and lake\r\nFirst floor With Rooof\r\nFacing North/Prime location\r\nArea : 220 m\r\nRoof area : 90 m\r\nReception / Kitchen  \r\nBedrooms: 4 ( masters:2)\r\nBathrooms: 3\r\nDriver room with bathroom\r\nFully finished\r\nFully furnished\r\nslot parking 2\r\nA/C\r\nprice : 14.500.000\r\n\r\nFor more details : 01286490599",
        "ownImages":  [
                          "C:\\Users\\used\\OneDrive\\Desktop\\بيع\\37\\WhatsApp Image 2026-04-09 at 10.36.26 AM.jpeg",
                          "C:\\Users\\used\\OneDrive\\Desktop\\بيع\\37\\WhatsApp Image 2026-04-09 at 10.36.28 AM.jpeg",
                          "C:\\Users\\used\\OneDrive\\Desktop\\بيع\\37\\WhatsApp Image 2026-04-09 at 10.36.29 AM.jpeg",
                          "C:\\Users\\used\\OneDrive\\Desktop\\بيع\\37\\WhatsApp Image 2026-04-09 at 10.36.31 AM.jpeg",
                          "C:\\Users\\used\\OneDrive\\Desktop\\بيع\\37\\WhatsApp Image 2026-04-09 at 10.36.33 AM.jpeg",
                          "C:\\Users\\used\\OneDrive\\Desktop\\بيع\\37\\WhatsApp Image 2026-04-09 at 10.36.35 AM.jpeg",
                          "C:\\Users\\used\\OneDrive\\Desktop\\بيع\\37\\WhatsApp Image 2026-04-09 at 10.36.38 AM.jpeg",
                          "C:\\Users\\used\\OneDrive\\Desktop\\بيع\\37\\WhatsApp Image 2026-04-09 at 10.36.40 AM.jpeg",
                          "C:\\Users\\used\\OneDrive\\Desktop\\بيع\\37\\WhatsApp Image 2026-04-09 at 10.36.44 AM.jpeg"
                      ]
    },
    {
        "folder":  "38",
        "txtName":  "lagoon villa with cabin for sale @h.txt",
        "txtPath":  "C:\\Users\\used\\OneDrive\\Desktop\\بيع\\38\\lagoon villa with cabin for sale @h.txt",
        "content":  "lagoon villa with cabin for sale @hacienda bay north cost \r\nview lagoon\r\nPrivate pool\r\nland:1400m\r\nBUA:460 m\r\n Consists of\r\nReception / Kitchen \r\nKitchen cabins\r\nReception cabins\r\nBedrooms: 5 (Master:5)\r\nBathroom: 7\r\nnany room with toilet \r\nDrive room with toilet \r\nFully furnished / Fully Finished \r\n5 A/Cs\r\nprice : 51.250.000\r\n\r\nPhone: 01286490599\r\n\r\nImage Investments offers you the best luxury homes with the best ways to pay in the finest areas: New Cairo - The capital city - October and Sheikh Zayed, North Coast - Ain Sokhna .\r\nThank you for choosing Image Investments",
        "ownImages":  [
                          "C:\\Users\\used\\OneDrive\\Desktop\\بيع\\38\\WhatsApp Image 2026-04-09 at 10.34.44 AM.jpeg",
                          "C:\\Users\\used\\OneDrive\\Desktop\\بيع\\38\\WhatsApp Image 2026-04-09 at 10.34.46 AM.jpeg",
                          "C:\\Users\\used\\OneDrive\\Desktop\\بيع\\38\\WhatsApp Image 2026-04-09 at 10.34.49 AM.jpeg",
                          "C:\\Users\\used\\OneDrive\\Desktop\\بيع\\38\\WhatsApp Image 2026-04-09 at 10.34.52 AM.jpeg",
                          "C:\\Users\\used\\OneDrive\\Desktop\\بيع\\38\\WhatsApp Image 2026-04-09 at 10.34.55 AM.jpeg",
                          "C:\\Users\\used\\OneDrive\\Desktop\\بيع\\38\\WhatsApp Image 2026-04-09 at 10.34.59 AM.jpeg",
                          "C:\\Users\\used\\OneDrive\\Desktop\\بيع\\38\\WhatsApp Image 2026-04-09 at 10.35.01 AM.jpeg"
                      ]
    },
    {
        "folder":  "39",
        "txtName":  "lagoon villa with cabin for sale @h.txt",
        "txtPath":  "C:\\Users\\used\\OneDrive\\Desktop\\بيع\\39\\lagoon villa with cabin for sale @h.txt",
        "content":  "lagoon villa with cabin for sale @hacienda bay north cost \r\nview lagoon\r\nPrivate pool\r\nland:1400m\r\nBUA:460 m\r\n Consists of\r\nReception / Kitchen \r\nKitchen cabins\r\nReception cabins\r\nBedrooms: 5 (Master:5)\r\nBathroom: 7\r\nnany room with toilet \r\nDrive room with toilet \r\nFully furnished / Fully Finished \r\n5 A/Cs\r\nprice : 50.000.000\r\n\r\nPhone: 01228397313\r\n\r\nImage Investments offers you the best luxury homes with the best ways to pay in the finest areas: New Cairo - The capital city - October and Sheikh Zayed, North Coast - Ain Sokhna .\r\nThank you for choosing Image Investments",
        "ownImages":  [
                          "C:\\Users\\used\\OneDrive\\Desktop\\بيع\\39\\WhatsApp Image 2026-04-09 at 10.30.10 AM (1).jpeg",
                          "C:\\Users\\used\\OneDrive\\Desktop\\بيع\\39\\WhatsApp Image 2026-04-09 at 10.30.10 AM.jpeg",
                          "C:\\Users\\used\\OneDrive\\Desktop\\بيع\\39\\WhatsApp Image 2026-04-09 at 10.30.11 AM (1).jpeg",
                          "C:\\Users\\used\\OneDrive\\Desktop\\بيع\\39\\WhatsApp Image 2026-04-09 at 10.30.11 AM (2).jpeg",
                          "C:\\Users\\used\\OneDrive\\Desktop\\بيع\\39\\WhatsApp Image 2026-04-09 at 10.30.11 AM (3).jpeg",
                          "C:\\Users\\used\\OneDrive\\Desktop\\بيع\\39\\WhatsApp Image 2026-04-09 at 10.30.11 AM (4).jpeg",
                          "C:\\Users\\used\\OneDrive\\Desktop\\بيع\\39\\WhatsApp Image 2026-04-09 at 10.30.11 AM (5).jpeg",
                          "C:\\Users\\used\\OneDrive\\Desktop\\بيع\\39\\WhatsApp Image 2026-04-09 at 10.30.11 AM.jpeg",
                          "C:\\Users\\used\\OneDrive\\Desktop\\بيع\\39\\WhatsApp Image 2026-04-09 at 10.30.12 AM (1).jpeg",
                          "C:\\Users\\used\\OneDrive\\Desktop\\بيع\\39\\WhatsApp Image 2026-04-09 at 10.30.12 AM (2).jpeg",
                          "C:\\Users\\used\\OneDrive\\Desktop\\بيع\\39\\WhatsApp Image 2026-04-09 at 10.30.12 AM (3).jpeg",
                          "C:\\Users\\used\\OneDrive\\Desktop\\بيع\\39\\WhatsApp Image 2026-04-09 at 10.30.12 AM (4).jpeg",
                          "C:\\Users\\used\\OneDrive\\Desktop\\بيع\\39\\WhatsApp Image 2026-04-09 at 10.30.12 AM.jpeg"
                      ]
    },
    {
        "folder":  "40",
        "txtName":  "أقل سعر وأفضل لوكيشن توين هاوس في أ.txt",
        "txtPath":  "C:\\Users\\used\\OneDrive\\Desktop\\بيع\\40\\أقل سعر وأفضل لوكيشن توين هاوس في أ.txt",
        "content":  "أقل سعر وأفضل لوكيشن توين هاوس في أمواچ_الساحل الشمالي🏕🌊🌊\r\nيطل على حمام سباحة مباشرة🏊‍♀️🤽‍♀️\r\nإطلالة مميزة على الكلوب هاوس🤽🏽🤾‍♂️🤸\r\nأرضي وأول\r\nمساحة الأرض: ٣١٠م\r\nمساحة المباني: ٢٣٠م\r\nيتكون من : ريسبشن\r\n٤ غرف نوم منهم ١ ماستر\r\n٣ حمام\r\nغرفة مربية بحمام\r\nغرفة سائق بحمام\r\nحديقة خاصة\r\nموقع مميز _ بحري صريح\r\nمكيف بالكامل\r\nيباع بالفرش والأجهزة\r\nكود : KH616\r\nللإستفسار: 01223233377\r\n\r\nالسعر 18.500.000",
        "ownImages":  [
                          "C:\\Users\\used\\OneDrive\\Desktop\\بيع\\40\\WhatsApp Image 2026-04-09 at 10.29.15 AM (1).jpeg",
                          "C:\\Users\\used\\OneDrive\\Desktop\\بيع\\40\\WhatsApp Image 2026-04-09 at 10.29.15 AM (2).jpeg",
                          "C:\\Users\\used\\OneDrive\\Desktop\\بيع\\40\\WhatsApp Image 2026-04-09 at 10.29.15 AM (3).jpeg",
                          "C:\\Users\\used\\OneDrive\\Desktop\\بيع\\40\\WhatsApp Image 2026-04-09 at 10.29.15 AM.jpeg",
                          "C:\\Users\\used\\OneDrive\\Desktop\\بيع\\40\\WhatsApp Image 2026-04-09 at 10.29.16 AM (1).jpeg",
                          "C:\\Users\\used\\OneDrive\\Desktop\\بيع\\40\\WhatsApp Image 2026-04-09 at 10.29.16 AM (2).jpeg",
                          "C:\\Users\\used\\OneDrive\\Desktop\\بيع\\40\\WhatsApp Image 2026-04-09 at 10.29.16 AM (3).jpeg",
                          "C:\\Users\\used\\OneDrive\\Desktop\\بيع\\40\\WhatsApp Image 2026-04-09 at 10.29.16 AM (4).jpeg",
                          "C:\\Users\\used\\OneDrive\\Desktop\\بيع\\40\\WhatsApp Image 2026-04-09 at 10.29.16 AM (5).jpeg",
                          "C:\\Users\\used\\OneDrive\\Desktop\\بيع\\40\\WhatsApp Image 2026-04-09 at 10.29.16 AM.jpeg"
                      ]
    },
    {
        "folder":  "41",
        "txtName":  "Marassi Marina.txt",
        "txtPath":  "C:\\Users\\used\\OneDrive\\Desktop\\بيع\\41\\Marassi Marina.txt",
        "content":  "Marassi Marina \r\nChalet For Sale \r\nPrime Location \r\nDirect Pool\r\n\r\nArea 172 m\r\n3 Bedrooms - 1 Master\r\n3 Bathrooms \r\nKitchen\r\nReception \r\nFully A/C\r\nFully Furnished \r\n\r\nPrice 33,000,000",
        "ownImages":  [
                          "C:\\Users\\used\\OneDrive\\Desktop\\بيع\\41\\WhatsApp Image 2026-04-09 at 10.25.26 AM (1).jpeg",
                          "C:\\Users\\used\\OneDrive\\Desktop\\بيع\\41\\WhatsApp Image 2026-04-09 at 10.25.26 AM (2).jpeg",
                          "C:\\Users\\used\\OneDrive\\Desktop\\بيع\\41\\WhatsApp Image 2026-04-09 at 10.25.26 AM.jpeg",
                          "C:\\Users\\used\\OneDrive\\Desktop\\بيع\\41\\WhatsApp Image 2026-04-09 at 10.25.27 AM (1).jpeg",
                          "C:\\Users\\used\\OneDrive\\Desktop\\بيع\\41\\WhatsApp Image 2026-04-09 at 10.25.27 AM (2).jpeg",
                          "C:\\Users\\used\\OneDrive\\Desktop\\بيع\\41\\WhatsApp Image 2026-04-09 at 10.25.27 AM.jpeg",
                          "C:\\Users\\used\\OneDrive\\Desktop\\بيع\\41\\WhatsApp Image 2026-04-09 at 10.25.28 AM (1).jpeg",
                          "C:\\Users\\used\\OneDrive\\Desktop\\بيع\\41\\WhatsApp Image 2026-04-09 at 10.25.28 AM (2).jpeg",
                          "C:\\Users\\used\\OneDrive\\Desktop\\بيع\\41\\WhatsApp Image 2026-04-09 at 10.25.28 AM (3).jpeg",
                          "C:\\Users\\used\\OneDrive\\Desktop\\بيع\\41\\WhatsApp Image 2026-04-09 at 10.25.28 AM (4).jpeg",
                          "C:\\Users\\used\\OneDrive\\Desktop\\بيع\\41\\WhatsApp Image 2026-04-09 at 10.25.28 AM.jpeg",
                          "C:\\Users\\used\\OneDrive\\Desktop\\بيع\\41\\WhatsApp Image 2026-04-09 at 10.25.29 AM (1).jpeg",
                          "C:\\Users\\used\\OneDrive\\Desktop\\بيع\\41\\WhatsApp Image 2026-04-09 at 10.25.29 AM.jpeg",
                          "C:\\Users\\used\\OneDrive\\Desktop\\بيع\\41\\WhatsApp Image 2026-04-09 at 10.25.30 AM (1).jpeg",
                          "C:\\Users\\used\\OneDrive\\Desktop\\بيع\\41\\WhatsApp Image 2026-04-09 at 10.25.30 AM.jpeg"
                      ]
    },
    {
        "folder":  "42",
        "txtName":  "Marassi Marina.txt",
        "txtPath":  "C:\\Users\\used\\OneDrive\\Desktop\\بيع\\42\\Marassi Marina.txt",
        "content":  "Marassi Marina \r\nChalet For Sale \r\nGround With Garden \r\nNear Pool \u0026 Marina \r\n\r\nArea 147 m\r\nGarden 65 m\r\n2 Bedrooms - 1 Master\r\n2 Bathrooms \r\nKitchen \r\nReception \r\nFully A/C\r\nFully Furnished \r\n\r\nD.p 22,000,000\r\nInstallments 2,885,000\r\nTotal 24,885,000\r\n01200092764",
        "ownImages":  [
                          "C:\\Users\\used\\OneDrive\\Desktop\\بيع\\42\\WhatsApp Image 2026-04-09 at 10.25.02 AM (1).jpeg",
                          "C:\\Users\\used\\OneDrive\\Desktop\\بيع\\42\\WhatsApp Image 2026-04-09 at 10.25.02 AM (2).jpeg",
                          "C:\\Users\\used\\OneDrive\\Desktop\\بيع\\42\\WhatsApp Image 2026-04-09 at 10.25.02 AM (3).jpeg",
                          "C:\\Users\\used\\OneDrive\\Desktop\\بيع\\42\\WhatsApp Image 2026-04-09 at 10.25.02 AM (4).jpeg",
                          "C:\\Users\\used\\OneDrive\\Desktop\\بيع\\42\\WhatsApp Image 2026-04-09 at 10.25.02 AM.jpeg",
                          "C:\\Users\\used\\OneDrive\\Desktop\\بيع\\42\\WhatsApp Image 2026-04-09 at 10.25.03 AM.jpeg"
                      ]
    },
    {
        "folder":  "43",
        "txtName":  null,
        "txtPath":  null,
        "content":  null,
        "ownImages":  [

                      ]
    },
    {
        "folder":  "44",
        "txtName":  null,
        "txtPath":  null,
        "content":  null,
        "ownImages":  [

                      ]
    },
    {
        "folder":  "45",
        "txtName":  null,
        "txtPath":  null,
        "content":  null,
        "ownImages":  [

                      ]
    }
]
